QCompute/__init__.py
QCompute/Calibration/__init__.py
QCompute/Define/Settings.py
QCompute/Define/Utils.py
QCompute/Define/__init__.py
QCompute/Module/__init__.py
QCompute/Module/MappingToBaiduQPUQianModule/__init__.py
QCompute/Module/MappingToIoPCASModule/__init__.py
QCompute/Module/MappingToIonAPMModule/__init__.py
QCompute/Module/UnrollCircuitToBaiduQPUQianModule/__init__.py
QCompute/Module/UnrollCircuitToIoPCASModule/__init__.py
QCompute/Module/UnrollCircuitToIonAPMModule/__init__.py
QCompute/OpenConvertor/__init__.py
QCompute/OpenConvertor/CircuitToDrawConsole/__init__.py
QCompute/OpenConvertor/CircuitToInternalStruct/__init__.py
QCompute/OpenConvertor/CircuitToIonQ/__init__.py
QCompute/OpenConvertor/CircuitToJson/__init__.py
QCompute/OpenConvertor/CircuitToQasm/__init__.py
QCompute/OpenConvertor/CircuitToQobj/__init__.py
QCompute/OpenConvertor/CircuitToXanaduSF/__init__.py
QCompute/OpenConvertor/InternalStructToCircuit/__init__.py
QCompute/OpenConvertor/IonQToCircuit/__init__.py
QCompute/OpenConvertor/JsonToCircuit/__init__.py
QCompute/OpenConvertor/QasmToCircuit/__init__.py
QCompute/OpenConvertor/QasmToCircuit/BNF_Antlr4/__init__.py
QCompute/OpenConvertor/QasmToCircuit/BNF_Antlr4/gen/QASMLexer.py
QCompute/OpenConvertor/QasmToCircuit/BNF_Antlr4/gen/QASMListener.py
QCompute/OpenConvertor/QasmToCircuit/BNF_Antlr4/gen/QASMParser.py
QCompute/OpenConvertor/QasmToCircuit/BNF_Antlr4/gen/QASMVisitor.py
QCompute/OpenConvertor/QasmToCircuit/BNF_Antlr4/gen/__init__.py
QCompute/OpenModule/__init__.py
QCompute/OpenModule/CompositeGateModule/__init__.py
QCompute/OpenModule/CompressGateModule/__init__.py
QCompute/OpenModule/CompressNoiseModule/__init__.py
QCompute/OpenModule/InverseCircuitModule/__init__.py
QCompute/OpenModule/ReverseCircuitModule/__init__.py
QCompute/OpenModule/UnrollCircuitModule/__init__.py
QCompute/OpenModule/UnrollNoiseModule/__init__.py
QCompute/OpenModule/UnrollProcedureModule/__init__.py
QCompute/OpenService/__init__.py
qcompute-3.3.5.dist-info/LICENSE
qcompute-3.3.5.dist-info/METADATA
qcompute-3.3.5.dist-info/WHEEL
qcompute-3.3.5.dist-info/top_level.txt
qcompute-3.3.5.dist-info/RECORD
