Metadata-Version: 2.1
Name: qcompute
Version: 3.3.5
Summary: QCompute is a Python-based quantum software development kit (SDK). It provides a full-stack programming experience for advanced users via hybrid quantum programming language features and a high-performance simulator.
Home-page: https://quantum.baidu.com
Author: Baidu Quantum
Author-email: quantum@baidu.com
License: Apache License 2.0
Requires-Python: >=3.8, <3.11
License-File: LICENSE
Requires-Dist: protobuf ==4.21.1
Requires-Dist: numpy >=1.17.3
Requires-Dist: requests ==2.31.0
Requires-Dist: bidict ==0.22.1
Requires-Dist: bce-python-sdk ==0.8.87
Requires-Dist: antlr4-python3-runtime ==4.13.0
Requires-Dist: py-expression-eval ==0.3.14
Requires-Dist: websocket-client ==1.6.1
Requires-Dist: tqdm >=4.5.0
Requires-Dist: nanoid ==2.0.0
Requires-Dist: multiprocess ==0.70.15
Requires-Dist: scipy >=1.8.0
Requires-Dist: matplotlib >=3.3.0
Requires-Dist: sympy ==1.12
Requires-Dist: pyprimes ==0.1
